[{"index": 0, "name": "jmp", "args": [null, null, null, "3"]},
 {"index": 1, "name": "input_port", "args": [0]},
 {"index": 2, "name": "output_port", "args": [0]},
 {"index": 3, "name": "li", "args": ["r0", null, null, "100"]},
 {"index": 4, "name": "dec", "args": ["sp", null, null, null]},
 {"index": 5, "name": "store", "args": ["ip", null, null, "sp"]},
 {"index": 6, "name": "jmp", "args": [null, null, null, "8"]},
 {"index": 7, "name": "halt", "args": [null, null, null, null]},
 {"index": 8, "name": "li", "args": ["r0", null, null, "74"]},
 {"index": 9, "name": "output", "args": ["r0", null, null, null]},
 {"index": 10, "name": "ld", "args": ["rr", null, null, "sp"]},
 {"index": 11, "name": "inc", "args": ["sp", null, null, null]},
 {"index": 12, "name": "inc", "args": ["rr", null, null, null]},
 {"index": 13, "name": "inc", "args": ["rr", null, null, null]},
 {"index": 14, "name": "jmp", "args": [null, null, null, "rr"]}]